[{"action": "PROCESS_START", "timestamp": 1715954292700}, {"action": "STEP_MENTION_SUGGESTION", "timestamp": 1715954292749}, {"action": "STEP_METION", "timestamp": 1715954292765}, {"action": "TOKEN_SELECTED", "data": {"index_in_document": 0, "index_in_sentence": 0, "pos_tag": "PRP", "sentence_index": 0, "text": "I"}, "timestamp": 1715954299940}, {"action": "MENTION_CREATED", "data": {"id": "1013935a-2c9b-410c-b4fe-c4e876e59744", "sentence_index": 0, "suggestion": false, "tag": "actor", "tokenInDocumentIndices": [0], "token_indices": [0]}, "timestamp": 1715954302269}, {"action": "TOKEN_SELECTED", "data": {"index_in_document": 18, "index_in_sentence": 4, "pos_tag": "PRP", "sentence_index": 1, "text": "I"}, "timestamp": 1715954308431}, {"action": "MENTION_CREATED", "data": {"id": "8c05a1ac-a627-475b-a3a5-585383e8c6c2", "sentence_index": 1, "suggestion": false, "tag": "actor", "tokenInDocumentIndices": [18], "token_indices": [4]}, "timestamp": 1715954309645}, {"action": "TOKEN_SELECTED", "data": {"index_in_document": 26, "index_in_sentence": 12, "pos_tag": "PRP", "sentence_index": 1, "text": "I"}, "timestamp": 1715954312794}, {"action": "MENTION_CREATED", "data": {"id": "1acfc351-f50b-49f9-ab01-6f6d82bbfa73", "sentence_index": 1, "suggestion": false, "tag": "actor", "tokenInDocumentIndices": [26], "token_indices": [12]}, "timestamp": 1715954314073}, {"action": "TOKEN_SELECTED", "data": {"index_in_document": 1, "index_in_sentence": 1, "pos_tag": "VBP", "sentence_index": 0, "text": "wait"}, "timestamp": 1715954316329}, {"action": "MENTION_CREATED", "data": {"id": "1a118e8f-6d80-40f1-8d9b-bbe9b3da5497", "sentence_index": 0, "suggestion": false, "tag": "activity", "tokenInDocumentIndices": [1], "token_indices": [1]}, "timestamp": 1715954319017}, {"action": "TOKEN_SELECTED", "data": {"index_in_document": 19, "index_in_sentence": 5, "pos_tag": "MD", "sentence_index": 1, "text": "must"}, "timestamp": 1715954329780}, {"action": "TOKEN_SELECTED", "data": {"index_in_document": 20, "index_in_sentence": 6, "pos_tag": "VB", "sentence_index": 1, "text": "ask"}, "timestamp": 1715954330446}, {"action": "TOKEN_DESELECTED", "data": {"index_in_document": 19, "index_in_sentence": 5, "pos_tag": "MD", "sentence_index": 1, "text": "must"}, "timestamp": 1715954331327}, {"action": "MENTION_CREATED", "data": {"id": "39650a48-67a3-4bbc-a555-ba1ec467e760", "sentence_index": 1, "suggestion": false, "tag": "activity", "tokenInDocumentIndices": [20], "token_indices": [6]}, "timestamp": 1715954332645}, {"action": "TOKEN_SELECTED", "data": {"index_in_document": 27, "index_in_sentence": 13, "pos_tag": "VBP", "sentence_index": 1, "text": "approve"}, "timestamp": 1715954335345}, {"action": "MENTION_CREATED", "data": {"id": "1fcfe9af-eb0e-444b-9506-6e4cc613901e", "sentence_index": 1, "suggestion": false, "tag": "activity", "tokenInDocumentIndices": [27], "token_indices": [13]}, "timestamp": 1715954336385}, {"action": "TOKEN_SELECTED", "data": {"index_in_document": 4, "index_in_sentence": 4, "pos_tag": "DT", "sentence_index": 0, "text": "the"}, "timestamp": 1715954344016}, {"action": "TOKEN_SELECTED", "data": {"index_in_document": 5, "index_in_sentence": 5, "pos_tag": "NN", "sentence_index": 0, "text": "job"}, "timestamp": 1715954345158}, {"action": "TOKEN_SELECTED", "data": {"index_in_document": 6, "index_in_sentence": 6, "pos_tag": "NN", "sentence_index": 0, "text": "description"}, "timestamp": 1715954347593}, {"action": "MENTION_CREATED", "data": {"id": "6368947d-bb0e-44e7-85b6-51555479cad7", "sentence_index": 0, "suggestion": false, "tag": "activity data", "tokenInDocumentIndices": [4, 5, 6], "token_indices": [4, 5, 6]}, "timestamp": 1715954350543}, {"action": "MENTION_SELECTED", "data": {"id": "1a118e8f-6d80-40f1-8d9b-bbe9b3da5497", "sentence_index": 0, "suggestion": false, "tag": "activity", "tokenInDocumentIndices": [1], "token_indices": [1], "tokens": [{"index_in_document": 1, "index_in_sentence": 1, "pos_tag": "VBP", "sentence_index": 0, "text": "wait"}]}, "timestamp": 1715954357809}, {"action": "MENTION_SUGGESTION_BOUNDS_UPDATED", "data": {"id": "1a118e8f-6d80-40f1-8d9b-bbe9b3da5497", "sentence_index": 0, "suggestion": false, "tag": "activity", "tokenInDocumentIndices": [1], "token_indices": [1], "tokens": [{"index_in_document": 1, "index_in_sentence": 1, "pos_tag": "VBP", "sentence_index": 0, "text": "wait"}]}, "timestamp": 1715954360495}, {"action": "MENTION_SUGGESTION_BOUNDS_UPDATED", "data": {"id": "1a118e8f-6d80-40f1-8d9b-bbe9b3da5497", "sentence_index": 0, "suggestion": false, "tag": "activity", "tokenInDocumentIndices": [1, 2], "token_indices": [1, 2], "tokens": [{"index_in_document": 1, "index_in_sentence": 1, "pos_tag": "VBP", "sentence_index": 0, "text": "wait"}, {"index_in_document": 2, "index_in_sentence": 2, "pos_tag": "TO", "sentence_index": 0, "text": "to"}]}, "timestamp": 1715954361406}, {"action": "TOKEN_SELECTED", "data": {"index_in_document": 7, "index_in_sentence": 7, "pos_tag": "IN", "sentence_index": 0, "text": "for"}, "timestamp": 1715954375072}, {"action": "TOKEN_SELECTED", "data": {"index_in_document": 8, "index_in_sentence": 8, "pos_tag": "NN", "sentence_index": 0, "text": "review"}, "timestamp": 1715954375881}, {"action": "MENTION_CREATED", "data": {"id": "dcfd9349-500e-4ada-9a77-bed71657863b", "sentence_index": 0, "suggestion": false, "tag": "further specification", "tokenInDocumentIndices": [7, 8], "token_indices": [7, 8]}, "timestamp": 1715954382209}, {"action": "TOKEN_SELECTED", "data": {"index_in_document": 22, "index_in_sentence": 8, "pos_tag": "NNS", "sentence_index": 1, "text": "corrections"}, "timestamp": 1715954401855}, {"action": "TOKEN_SELECTED", "data": {"index_in_document": 21, "index_in_sentence": 7, "pos_tag": "IN", "sentence_index": 1, "text": "for"}, "timestamp": 1715954403073}, {"action": "MENTION_CREATED", "data": {"id": "04674ef9-281d-40bf-bb4c-e63a2c4a091c", "sentence_index": 1, "suggestion": false, "tag": "further specification", "tokenInDocumentIndices": [21, 22], "token_indices": [7, 8]}, "timestamp": 1715954407668}, {"action": "TOKEN_SELECTED", "data": {"index_in_document": 14, "index_in_sentence": 0, "pos_tag": "IN", "sentence_index": 1, "text": "Under"}, "timestamp": 1715954420037}, {"action": "TOKEN_SELECTED", "data": {"index_in_document": 15, "index_in_sentence": 1, "pos_tag": "JJ", "sentence_index": 1, "text": "certain"}, "timestamp": 1715954424262}, {"action": "TOKEN_SELECTED", "data": {"index_in_document": 16, "index_in_sentence": 2, "pos_tag": "NNS", "sentence_index": 1, "text": "circumstances"}, "timestamp": 1715954424999}, {"action": "MENTION_CREATED", "data": {"id": "f94fe127-0945-463c-b7cf-8fa9ed5d8c15", "sentence_index": 1, "suggestion": false, "tag": "xor gateway", "tokenInDocumentIndices": [14, 15, 16], "token_indices": [0, 1, 2]}, "timestamp": 1715954443325}, {"action": "TOKEN_SELECTED", "data": {"index_in_document": 25, "index_in_sentence": 11, "pos_tag": "RB", "sentence_index": 1, "text": "otherwise"}, "timestamp": 1715954444536}, {"action": "MENTION_CREATED", "data": {"id": "dc33d327-1c5c-42f3-9a9f-92713a1f54b9", "sentence_index": 1, "suggestion": false, "tag": "xor gateway", "tokenInDocumentIndices": [25], "token_indices": [11]}, "timestamp": 1715954446067}, {"action": "MENTION_SELECTED", "data": {"id": "f94fe127-0945-463c-b7cf-8fa9ed5d8c15", "sentence_index": 1, "suggestion": false, "tag": "xor gateway", "tokenInDocumentIndices": [14, 15, 16], "token_indices": [0, 1, 2], "tokens": [{"index_in_document": 14, "index_in_sentence": 0, "pos_tag": "IN", "sentence_index": 1, "text": "Under"}, {"index_in_document": 15, "index_in_sentence": 1, "pos_tag": "JJ", "sentence_index": 1, "text": "certain"}, {"index_in_document": 16, "index_in_sentence": 2, "pos_tag": "NNS", "sentence_index": 1, "text": "circumstances"}]}, "timestamp": 1715954458568}, {"action": "MENTION_SUGGESTION_BOUNDS_UPDATED", "data": {"id": "f94fe127-0945-463c-b7cf-8fa9ed5d8c15", "sentence_index": 1, "suggestion": false, "tag": "xor gateway", "tokenInDocumentIndices": [14, 15, 16], "token_indices": [0, 1, 2], "tokens": [{"index_in_document": 14, "index_in_sentence": 0, "pos_tag": "IN", "sentence_index": 1, "text": "Under"}, {"index_in_document": 15, "index_in_sentence": 1, "pos_tag": "JJ", "sentence_index": 1, "text": "certain"}, {"index_in_document": 16, "index_in_sentence": 2, "pos_tag": "NNS", "sentence_index": 1, "text": "circumstances"}]}, "timestamp": 1715954462342}, {"action": "TOKEN_SELECTED", "data": {"index_in_document": 16, "index_in_sentence": 2, "pos_tag": "NNS", "sentence_index": 1, "text": "circumstances"}, "timestamp": 1715954463000}, {"action": "MENTION_SELECTED", "data": {"id": "f94fe127-0945-463c-b7cf-8fa9ed5d8c15", "sentence_index": 1, "suggestion": false, "tag": "xor gateway", "tokenInDocumentIndices": [14, 15], "token_indices": [0, 1], "tokens": [{"index_in_document": 14, "index_in_sentence": 0, "pos_tag": "IN", "sentence_index": 1, "text": "Under"}, {"index_in_document": 15, "index_in_sentence": 1, "pos_tag": "JJ", "sentence_index": 1, "text": "certain"}]}, "timestamp": 1715954464578}, {"action": "MENTION_SUGGESTION_BOUNDS_UPDATED", "data": {"id": "f94fe127-0945-463c-b7cf-8fa9ed5d8c15", "sentence_index": 1, "suggestion": false, "tag": "xor gateway", "tokenInDocumentIndices": [14, 15], "token_indices": [0, 1], "tokens": [{"index_in_document": 14, "index_in_sentence": 0, "pos_tag": "IN", "sentence_index": 1, "text": "Under"}, {"index_in_document": 15, "index_in_sentence": 1, "pos_tag": "JJ", "sentence_index": 1, "text": "certain"}]}, "timestamp": 1715954466127}, {"action": "TOKEN_SELECTED", "data": {"index_in_document": 15, "index_in_sentence": 1, "pos_tag": "JJ", "sentence_index": 1, "text": "certain"}, "timestamp": 1715954467384}, {"action": "TOKEN_SELECTED", "data": {"index_in_document": 16, "index_in_sentence": 2, "pos_tag": "NNS", "sentence_index": 1, "text": "circumstances"}, "timestamp": 1715954468019}, {"action": "MENTION_CREATED", "data": {"id": "bf7aadaa-73f7-4830-9237-175da42341c9", "sentence_index": 1, "suggestion": false, "tag": "condition specification", "tokenInDocumentIndices": [15, 16], "token_indices": [1, 2]}, "timestamp": 1715954469746}, {"action": "TOKEN_SELECTED", "data": {"index_in_document": 29, "index_in_sentence": 15, "pos_tag": "NN", "sentence_index": 1, "text": "job"}, "timestamp": 1715954473824}, {"action": "TOKEN_SELECTED", "data": {"index_in_document": 28, "index_in_sentence": 14, "pos_tag": "DT", "sentence_index": 1, "text": "the"}, "timestamp": 1715954474962}, {"action": "TOKEN_SELECTED", "data": {"index_in_document": 30, "index_in_sentence": 16, "pos_tag": "NN", "sentence_index": 1, "text": "description"}, "timestamp": 1715954475503}, {"action": "MENTION_CREATED", "data": {"id": "3042f39a-a332-4f29-8712-140abce85ca9", "sentence_index": 1, "suggestion": false, "tag": "activity data", "tokenInDocumentIndices": [28, 29, 30], "token_indices": [14, 15, 16]}, "timestamp": 1715954476342}, {"action": "PROCESS_END", "timestamp": 1715954481112}, {"action": "STEP_ENTITIES", "timestamp": 1715954487538}, {"action": "MENTION_SELECTED", "data": {"id": "1013935a-2c9b-410c-b4fe-c4e876e59744", "sentence_index": 0, "suggestion": false, "tag": "actor", "tokenInDocumentIndices": [0], "token_indices": [0], "tokens": [{"index_in_document": 0, "index_in_sentence": 0, "pos_tag": "PRP", "sentence_index": 0, "text": "I"}]}, "timestamp": 1715954492304}, {"action": "MENTION_SELECTED", "data": {"id": "8c05a1ac-a627-475b-a3a5-585383e8c6c2", "sentence_index": 1, "suggestion": false, "tag": "actor", "tokenInDocumentIndices": [18], "token_indices": [4], "tokens": [{"index_in_document": 18, "index_in_sentence": 4, "pos_tag": "PRP", "sentence_index": 1, "text": "I"}]}, "timestamp": 1715954493556}, {"action": "MENTION_SELECTED", "data": {"id": "1acfc351-f50b-49f9-ab01-6f6d82bbfa73", "sentence_index": 1, "suggestion": false, "tag": "actor", "tokenInDocumentIndices": [26], "token_indices": [12], "tokens": [{"index_in_document": 26, "index_in_sentence": 12, "pos_tag": "PRP", "sentence_index": 1, "text": "I"}]}, "timestamp": 1715954495580}, {"action": "ENTITY_GROUPED", "data": {"mention_indices": [0, 1, 2]}, "timestamp": 1715954497230}, {"action": "MENTION_SELECTED", "data": {"id": "6368947d-bb0e-44e7-85b6-51555479cad7", "sentence_index": 0, "suggestion": false, "tag": "activity data", "tokenInDocumentIndices": [4, 5, 6], "token_indices": [4, 5, 6], "tokens": [{"index_in_document": 4, "index_in_sentence": 4, "pos_tag": "DT", "sentence_index": 0, "text": "the"}, {"index_in_document": 5, "index_in_sentence": 5, "pos_tag": "NN", "sentence_index": 0, "text": "job"}, {"index_in_document": 6, "index_in_sentence": 6, "pos_tag": "NN", "sentence_index": 0, "text": "description"}]}, "timestamp": 1715954500206}, {"action": "MENTION_SELECTED", "data": {"id": "3042f39a-a332-4f29-8712-140abce85ca9", "sentence_index": 1, "suggestion": false, "tag": "activity data", "tokenInDocumentIndices": [28, 29, 30], "token_indices": [14, 15, 16], "tokens": [{"index_in_document": 28, "index_in_sentence": 14, "pos_tag": "DT", "sentence_index": 1, "text": "the"}, {"index_in_document": 29, "index_in_sentence": 15, "pos_tag": "NN", "sentence_index": 1, "text": "job"}, {"index_in_document": 30, "index_in_sentence": 16, "pos_tag": "NN", "sentence_index": 1, "text": "description"}]}, "timestamp": 1715954501138}, {"action": "ENTITY_GROUPED", "data": {"mention_indices": [6, 12]}, "timestamp": 1715954502383}, {"action": "STEP_RELATION_SUGGESTION", "timestamp": 1715954505573}, {"action": "STEP_RELATIONS", "timestamp": 1715954505590}, {"action": "MENTION_SELECTED", "data": {"id": "1a118e8f-6d80-40f1-8d9b-bbe9b3da5497", "sentence_index": 0, "suggestion": false, "tag": "activity", "tokenInDocumentIndices": [1, 2, 3], "token_indices": [1, 2, 3], "tokens": [{"index_in_document": 1, "index_in_sentence": 1, "pos_tag": "VBP", "sentence_index": 0, "text": "wait"}, {"index_in_document": 2, "index_in_sentence": 2, "pos_tag": "TO", "sentence_index": 0, "text": "to"}, {"index_in_document": 3, "index_in_sentence": 3, "pos_tag": "VB", "sentence_index": 0, "text": "get"}]}, "timestamp": 1715954512227}, {"action": "MENTION_SELECTED", "data": {"id": "1013935a-2c9b-410c-b4fe-c4e876e59744", "sentence_index": 0, "suggestion": false, "tag": "actor", "tokenInDocumentIndices": [0], "token_indices": [0], "tokens": [{"index_in_document": 0, "index_in_sentence": 0, "pos_tag": "PRP", "sentence_index": 0, "text": "I"}]}, "timestamp": 1715954514189}, {"action": "RELATION_CREATED", "data": {"evidence": [0], "head": 3, "id": "c3927363-349e-4cda-ba53-270b6cc4d80b", "isCondition": false, "marked": false, "suggestion": false, "tag": "actor performer", "tail": 0}, "timestamp": 1715954517526}, {"action": "MENTION_SELECTED", "data": {"id": "39650a48-67a3-4bbc-a555-ba1ec467e760", "sentence_index": 1, "suggestion": false, "tag": "activity", "tokenInDocumentIndices": [20], "token_indices": [6], "tokens": [{"index_in_document": 20, "index_in_sentence": 6, "pos_tag": "VB", "sentence_index": 1, "text": "ask"}]}, "timestamp": 1715954519151}, {"action": "MENTION_SELECTED", "data": {"id": "8c05a1ac-a627-475b-a3a5-585383e8c6c2", "sentence_index": 1, "suggestion": false, "tag": "actor", "tokenInDocumentIndices": [18], "token_indices": [4], "tokens": [{"index_in_document": 18, "index_in_sentence": 4, "pos_tag": "PRP", "sentence_index": 1, "text": "I"}]}, "timestamp": 1715954519967}, {"action": "RELATION_CREATED", "data": {"evidence": [1], "head": 4, "id": "cbbf93f9-f5cd-4128-8ba4-98523c4bc905", "isCondition": false, "marked": false, "suggestion": false, "tag": "actor performer", "tail": 1}, "timestamp": 1715954521506}, {"action": "MENTION_SELECTED", "data": {"id": "1fcfe9af-eb0e-444b-9506-6e4cc613901e", "sentence_index": 1, "suggestion": false, "tag": "activity", "tokenInDocumentIndices": [27], "token_indices": [13], "tokens": [{"index_in_document": 27, "index_in_sentence": 13, "pos_tag": "VBP", "sentence_index": 1, "text": "approve"}]}, "timestamp": 1715954522684}, {"action": "MENTION_SELECTED", "data": {"id": "1acfc351-f50b-49f9-ab01-6f6d82bbfa73", "sentence_index": 1, "suggestion": false, "tag": "actor", "tokenInDocumentIndices": [26], "token_indices": [12], "tokens": [{"index_in_document": 26, "index_in_sentence": 12, "pos_tag": "PRP", "sentence_index": 1, "text": "I"}]}, "timestamp": 1715954523741}, {"action": "RELATION_CREATED", "data": {"evidence": [1], "head": 5, "id": "85d4c4a1-a69c-4963-aa6a-68b01dabda34", "isCondition": false, "marked": false, "suggestion": false, "tag": "actor performer", "tail": 2}, "timestamp": 1715954525156}, {"action": "MENTION_SELECTED", "data": {"id": "1a118e8f-6d80-40f1-8d9b-bbe9b3da5497", "sentence_index": 0, "suggestion": false, "tag": "activity", "tokenInDocumentIndices": [1, 2, 3], "token_indices": [1, 2, 3], "tokens": [{"index_in_document": 1, "index_in_sentence": 1, "pos_tag": "VBP", "sentence_index": 0, "text": "wait"}, {"index_in_document": 2, "index_in_sentence": 2, "pos_tag": "TO", "sentence_index": 0, "text": "to"}, {"index_in_document": 3, "index_in_sentence": 3, "pos_tag": "VB", "sentence_index": 0, "text": "get"}]}, "timestamp": 1715954530725}, {"action": "MENTION_SELECTED", "data": {"id": "6368947d-bb0e-44e7-85b6-51555479cad7", "sentence_index": 0, "suggestion": false, "tag": "activity data", "tokenInDocumentIndices": [4, 5, 6], "token_indices": [4, 5, 6], "tokens": [{"index_in_document": 4, "index_in_sentence": 4, "pos_tag": "DT", "sentence_index": 0, "text": "the"}, {"index_in_document": 5, "index_in_sentence": 5, "pos_tag": "NN", "sentence_index": 0, "text": "job"}, {"index_in_document": 6, "index_in_sentence": 6, "pos_tag": "NN", "sentence_index": 0, "text": "description"}]}, "timestamp": 1715954531753}, {"action": "RELATION_CREATED", "data": {"evidence": [0], "head": 3, "id": "af5e7719-dfed-4e83-a449-f04680ff0896", "isCondition": false, "marked": false, "suggestion": false, "tag": "uses", "tail": 6}, "timestamp": 1715954533222}, {"action": "MENTION_SELECTED", "data": {"id": "39650a48-67a3-4bbc-a555-ba1ec467e760", "sentence_index": 1, "suggestion": false, "tag": "activity", "tokenInDocumentIndices": [20], "token_indices": [6], "tokens": [{"index_in_document": 20, "index_in_sentence": 6, "pos_tag": "VB", "sentence_index": 1, "text": "ask"}]}, "timestamp": 1715954539795}, {"action": "MENTION_SELECTED", "data": {"id": "04674ef9-281d-40bf-bb4c-e63a2c4a091c", "sentence_index": 1, "suggestion": false, "tag": "further specification", "tokenInDocumentIndices": [21, 22], "token_indices": [7, 8], "tokens": [{"index_in_document": 21, "index_in_sentence": 7, "pos_tag": "IN", "sentence_index": 1, "text": "for"}, {"index_in_document": 22, "index_in_sentence": 8, "pos_tag": "NNS", "sentence_index": 1, "text": "corrections"}]}, "timestamp": 1715954541646}, {"action": "RELATION_CREATED", "data": {"evidence": [1], "head": 4, "id": "abc1d66e-347e-4a20-b1af-cea96cc9349e", "isCondition": false, "marked": false, "suggestion": false, "tag": "further specification", "tail": 8}, "timestamp": 1715954543417}, {"action": "MENTION_SELECTED", "data": {"id": "1fcfe9af-eb0e-444b-9506-6e4cc613901e", "sentence_index": 1, "suggestion": false, "tag": "activity", "tokenInDocumentIndices": [27], "token_indices": [13], "tokens": [{"index_in_document": 27, "index_in_sentence": 13, "pos_tag": "VBP", "sentence_index": 1, "text": "approve"}]}, "timestamp": 1715954546459}, {"action": "MENTION_SELECTED", "data": {"id": "3042f39a-a332-4f29-8712-140abce85ca9", "sentence_index": 1, "suggestion": false, "tag": "activity data", "tokenInDocumentIndices": [28, 29, 30], "token_indices": [14, 15, 16], "tokens": [{"index_in_document": 28, "index_in_sentence": 14, "pos_tag": "DT", "sentence_index": 1, "text": "the"}, {"index_in_document": 29, "index_in_sentence": 15, "pos_tag": "NN", "sentence_index": 1, "text": "job"}, {"index_in_document": 30, "index_in_sentence": 16, "pos_tag": "NN", "sentence_index": 1, "text": "description"}]}, "timestamp": 1715954547685}, {"action": "RELATION_CREATED", "data": {"evidence": [1], "head": 5, "id": "0a09f7f7-196e-493a-af80-6967e270ae15", "isCondition": false, "marked": false, "suggestion": false, "tag": "uses", "tail": 12}, "timestamp": 1715954548939}, {"action": "MENTION_SELECTED", "data": {"id": "f94fe127-0945-463c-b7cf-8fa9ed5d8c15", "sentence_index": 1, "suggestion": false, "tag": "xor gateway", "tokenInDocumentIndices": [14], "token_indices": [0], "tokens": [{"index_in_document": 14, "index_in_sentence": 0, "pos_tag": "IN", "sentence_index": 1, "text": "Under"}]}, "timestamp": 1715954556664}, {"action": "MENTION_SELECTED", "data": {"id": "dc33d327-1c5c-42f3-9a9f-92713a1f54b9", "sentence_index": 1, "suggestion": false, "tag": "xor gateway", "tokenInDocumentIndices": [25], "token_indices": [11], "tokens": [{"index_in_document": 25, "index_in_sentence": 11, "pos_tag": "RB", "sentence_index": 1, "text": "otherwise"}]}, "timestamp": 1715954557870}, {"action": "RELATION_CREATED", "data": {"evidence": [1], "head": 9, "id": "d111d76e-2181-40be-a93e-9729bc089404", "isCondition": false, "marked": false, "suggestion": false, "tag": "same gateway", "tail": 10}, "timestamp": 1715954560984}, {"action": "MENTION_SELECTED", "data": {"id": "f94fe127-0945-463c-b7cf-8fa9ed5d8c15", "sentence_index": 1, "suggestion": false, "tag": "xor gateway", "tokenInDocumentIndices": [14], "token_indices": [0], "tokens": [{"index_in_document": 14, "index_in_sentence": 0, "pos_tag": "IN", "sentence_index": 1, "text": "Under"}]}, "timestamp": 1715954564592}, {"action": "MENTION_SELECTED", "data": {"id": "bf7aadaa-73f7-4830-9237-175da42341c9", "sentence_index": 1, "suggestion": false, "tag": "condition specification", "tokenInDocumentIndices": [15, 16], "token_indices": [1, 2], "tokens": [{"index_in_document": 15, "index_in_sentence": 1, "pos_tag": "JJ", "sentence_index": 1, "text": "certain"}, {"index_in_document": 16, "index_in_sentence": 2, "pos_tag": "NNS", "sentence_index": 1, "text": "circumstances"}]}, "timestamp": 1715954567221}, {"action": "RELATION_CREATED", "data": {"evidence": [1], "head": 9, "id": "4ec991b8-d426-4d3e-b80c-f5dc7d0fa451", "isCondition": true, "marked": false, "suggestion": false, "tag": "condition specification", "tail": 11}, "timestamp": 1715954569187}, {"action": "MENTION_SELECTED", "data": {"id": "1a118e8f-6d80-40f1-8d9b-bbe9b3da5497", "sentence_index": 0, "suggestion": false, "tag": "activity", "tokenInDocumentIndices": [1, 2, 3], "token_indices": [1, 2, 3], "tokens": [{"index_in_document": 1, "index_in_sentence": 1, "pos_tag": "VBP", "sentence_index": 0, "text": "wait"}, {"index_in_document": 2, "index_in_sentence": 2, "pos_tag": "TO", "sentence_index": 0, "text": "to"}, {"index_in_document": 3, "index_in_sentence": 3, "pos_tag": "VB", "sentence_index": 0, "text": "get"}]}, "timestamp": 1715954584739}, {"action": "MENTION_SELECTED", "data": {"id": "f94fe127-0945-463c-b7cf-8fa9ed5d8c15", "sentence_index": 1, "suggestion": false, "tag": "xor gateway", "tokenInDocumentIndices": [14], "token_indices": [0], "tokens": [{"index_in_document": 14, "index_in_sentence": 0, "pos_tag": "IN", "sentence_index": 1, "text": "Under"}]}, "timestamp": 1715954598295}, {"action": "MENTION_SELECTED", "data": {"id": "39650a48-67a3-4bbc-a555-ba1ec467e760", "sentence_index": 1, "suggestion": false, "tag": "activity", "tokenInDocumentIndices": [20], "token_indices": [6], "tokens": [{"index_in_document": 20, "index_in_sentence": 6, "pos_tag": "VB", "sentence_index": 1, "text": "ask"}]}, "timestamp": 1715954599612}, {"action": "RELATION_CREATED", "data": {"evidence": [1], "head": 9, "id": "631f99f3-83a2-4a31-83ae-c478d50e9cec", "isCondition": false, "marked": false, "suggestion": false, "tag": "flow", "tail": 4}, "timestamp": 1715954600885}, {"action": "MENTION_SELECTED", "data": {"id": "dc33d327-1c5c-42f3-9a9f-92713a1f54b9", "sentence_index": 1, "suggestion": false, "tag": "xor gateway", "tokenInDocumentIndices": [25], "token_indices": [11], "tokens": [{"index_in_document": 25, "index_in_sentence": 11, "pos_tag": "RB", "sentence_index": 1, "text": "otherwise"}]}, "timestamp": 1715954609889}, {"action": "MENTION_SELECTED", "data": {"id": "1fcfe9af-eb0e-444b-9506-6e4cc613901e", "sentence_index": 1, "suggestion": false, "tag": "activity", "tokenInDocumentIndices": [27], "token_indices": [13], "tokens": [{"index_in_document": 27, "index_in_sentence": 13, "pos_tag": "VBP", "sentence_index": 1, "text": "approve"}]}, "timestamp": 1715954610646}, {"action": "RELATION_CREATED", "data": {"evidence": [1], "head": 10, "id": "48d1fc27-7704-4d00-8275-747e9db73d3a", "isCondition": false, "marked": false, "suggestion": false, "tag": "flow", "tail": 5}, "timestamp": 1715954611919}, {"action": "MENTION_SELECTED", "data": {"id": "1a118e8f-6d80-40f1-8d9b-bbe9b3da5497", "sentence_index": 0, "suggestion": false, "tag": "activity", "tokenInDocumentIndices": [1, 2, 3], "token_indices": [1, 2, 3], "tokens": [{"index_in_document": 1, "index_in_sentence": 1, "pos_tag": "VBP", "sentence_index": 0, "text": "wait"}, {"index_in_document": 2, "index_in_sentence": 2, "pos_tag": "TO", "sentence_index": 0, "text": "to"}, {"index_in_document": 3, "index_in_sentence": 3, "pos_tag": "VB", "sentence_index": 0, "text": "get"}]}, "timestamp": 1715954624679}, {"action": "MENTION_SELECTED", "data": {"id": "39650a48-67a3-4bbc-a555-ba1ec467e760", "sentence_index": 1, "suggestion": false, "tag": "activity", "tokenInDocumentIndices": [20], "token_indices": [6], "tokens": [{"index_in_document": 20, "index_in_sentence": 6, "pos_tag": "VB", "sentence_index": 1, "text": "ask"}]}, "timestamp": 1715954625999}, {"action": "RELATION_CREATED", "data": {"evidence": [0, 1], "head": 3, "id": "7b8e4cb0-5895-4d0d-9cb0-89fc5c8745c3", "isCondition": false, "marked": false, "suggestion": false, "tag": "flow", "tail": 4}, "timestamp": 1715954627130}, {"action": "MENTION_SELECTED", "data": {"id": "39650a48-67a3-4bbc-a555-ba1ec467e760", "sentence_index": 1, "suggestion": false, "tag": "activity", "tokenInDocumentIndices": [20], "token_indices": [6], "tokens": [{"index_in_document": 20, "index_in_sentence": 6, "pos_tag": "VB", "sentence_index": 1, "text": "ask"}]}, "timestamp": 1715954633530}, {"action": "MENTION_SELECTED", "data": {"id": "1fcfe9af-eb0e-444b-9506-6e4cc613901e", "sentence_index": 1, "suggestion": false, "tag": "activity", "tokenInDocumentIndices": [27], "token_indices": [13], "tokens": [{"index_in_document": 27, "index_in_sentence": 13, "pos_tag": "VBP", "sentence_index": 1, "text": "approve"}]}, "timestamp": 1715954635394}, {"action": "RELATION_CREATED", "data": {"evidence": [1], "head": 4, "id": "17336d3a-5ff7-41df-a5c9-9eb58ea16229", "isCondition": false, "marked": false, "suggestion": false, "tag": "flow", "tail": 5}, "timestamp": 1715954636822}, {"action": "MENTION_SELECTED", "data": {"id": "1a118e8f-6d80-40f1-8d9b-bbe9b3da5497", "sentence_index": 0, "suggestion": false, "tag": "activity", "tokenInDocumentIndices": [1, 2, 3], "token_indices": [1, 2, 3], "tokens": [{"index_in_document": 1, "index_in_sentence": 1, "pos_tag": "VBP", "sentence_index": 0, "text": "wait"}, {"index_in_document": 2, "index_in_sentence": 2, "pos_tag": "TO", "sentence_index": 0, "text": "to"}, {"index_in_document": 3, "index_in_sentence": 3, "pos_tag": "VB", "sentence_index": 0, "text": "get"}]}, "timestamp": 1715954648086}, {"action": "MENTION_SELECTED", "data": {"id": "dcfd9349-500e-4ada-9a77-bed71657863b", "sentence_index": 0, "suggestion": false, "tag": "further specification", "tokenInDocumentIndices": [7, 8], "token_indices": [7, 8], "tokens": [{"index_in_document": 7, "index_in_sentence": 7, "pos_tag": "IN", "sentence_index": 0, "text": "for"}, {"index_in_document": 8, "index_in_sentence": 8, "pos_tag": "NN", "sentence_index": 0, "text": "review"}]}, "timestamp": 1715954649400}, {"action": "RELATION_CREATED", "data": {"evidence": [0], "head": 3, "id": "0aaf5dcd-b4b6-4b05-95f9-19d99a572405", "isCondition": false, "marked": false, "suggestion": false, "tag": "further specification", "tail": 7}, "timestamp": 1715954651661}, {"action": "PROCESS_END", "timestamp": 1715954666233}]